torob_less_price_finder/__init__.py
torob_less_price_finder/cli.py
torob_less_price_finder-0.0.1.dist-info/licenses/LICENSE
torob_less_price_finder-0.0.1.dist-info/METADATA
torob_less_price_finder-0.0.1.dist-info/WHEEL
torob_less_price_finder-0.0.1.dist-info/entry_points.txt
torob_less_price_finder-0.0.1.dist-info/top_level.txt
torob_less_price_finder-0.0.1.dist-info/RECORD
