Metadata-Version: 2.4
Name: torob-less-price-finder
Version: 0.0.1
Summary: A simple web scraper to find the lowest price of a product on Torob.
Author-email: Your Name <you@example.com>
Project-URL: Homepage, https://github.com/your-username/torob-less-price-finder
Project-URL: Bug Tracker, https://github.com/your-username/torob-less-price-finder/issues
Classifier: Programming Language :: Python :: 3
Classifier: License :: OSI Approved :: MIT License
Classifier: Operating System :: OS Independent
Requires-Python: >=3.7
License-File: LICENSE
Requires-Dist: requests
Requires-Dist: beautifulsoup4
Requires-Dist: python-dotenv
Dynamic: license-file
